smcplaus/__init__.py
smcplaus/constants.py
smcplaus/exceptions.py
smcplaus/language/__init__.py
smcplaus/language/connectives.py
smcplaus/language/formula.py
smcplaus/language/propositional_variable.py
smcplaus/models/__init__.py
smcplaus/models/plausibility_frame.py
smcplaus/models/plausibility_model.py
smcplaus/models/state.py
smcplaus/protocols/__init__.py
smcplaus/protocols/digraph_representable_structure.py
smcplaus/protocols/json_serializable_structure.py
smcplaus/py.typed
smcplaus-1.1.6.dist-info/LICENSE
smcplaus-1.1.6.dist-info/METADATA
smcplaus-1.1.6.dist-info/WHEEL
smcplaus-1.1.6.dist-info/RECORD
