Metadata-Version: 2.1
Name: smcplaus
Version: 1.1.6
Summary: A symbolic model checker for the single-agent plausibility models of dynamic epistemic logic
Home-page: https://gitlab.com/dqalvarez/smcplaus
License: MIT
Keywords: belief revision,dynamic epistemic logic,logic,plausibility,symbolic model checking
Author: David Quinn Alvarez
Author-email: dqalvarez@proton.me
Maintainer: David Quinn Alvarez
Maintainer-email: dqalvarez@proton.me
Requires-Python: >=3.11,<4.0
Classifier: License :: OSI Approved :: MIT License
Classifier: Programming Language :: Python :: 3
Classifier: Programming Language :: Python :: 3.11
Classifier: Programming Language :: Python :: 3.12
Classifier: Programming Language :: Python :: 3.13
Requires-Dist: graphviz (>=0.20.1,<0.21.0)
Project-URL: Repository, https://gitlab.com/dqalvarez/smcplaus
